odoo/addons/l10n_it_financial_statements_report/README.rst
odoo/addons/l10n_it_financial_statements_report/__init__.py
odoo/addons/l10n_it_financial_statements_report/__manifest__.py
odoo/addons/l10n_it_financial_statements_report/hooks.py
odoo/addons/l10n_it_financial_statements_report/data/account_type.xml
odoo/addons/l10n_it_financial_statements_report/i18n/it.po
odoo/addons/l10n_it_financial_statements_report/i18n/l10n_it_financial_statements_report.pot
odoo/addons/l10n_it_financial_statements_report/migrations/14.0.1.0.0/pre-migrate.py
odoo/addons/l10n_it_financial_statements_report/migrations/14.0.1.1.3/post-migrate.py
odoo/addons/l10n_it_financial_statements_report/models/__init__.py
odoo/addons/l10n_it_financial_statements_report/models/account_account.py
odoo/addons/l10n_it_financial_statements_report/models/account_type.py
odoo/addons/l10n_it_financial_statements_report/readme/CONTRIBUTORS.rst
odoo/addons/l10n_it_financial_statements_report/readme/CREDITS.rst
odoo/addons/l10n_it_financial_statements_report/readme/DESCRIPTION.rst
odoo/addons/l10n_it_financial_statements_report/readme/INSTALL.rst
odoo/addons/l10n_it_financial_statements_report/readme/USAGE.rst
odoo/addons/l10n_it_financial_statements_report/report/__init__.py
odoo/addons/l10n_it_financial_statements_report/report/financial_statements_report.py
odoo/addons/l10n_it_financial_statements_report/report/financial_statements_report_xlsx.py
odoo/addons/l10n_it_financial_statements_report/report/reports.xml
odoo/addons/l10n_it_financial_statements_report/report/templates/financial_statements_report.xml
odoo/addons/l10n_it_financial_statements_report/static/description/icon.png
odoo/addons/l10n_it_financial_statements_report/static/description/index.html
odoo/addons/l10n_it_financial_statements_report/static/src/js/action_manager_report.js
odoo/addons/l10n_it_financial_statements_report/static/src/js/client_action.js
odoo/addons/l10n_it_financial_statements_report/tests/__init__.py
odoo14_addon_l10n_it_financial_statements_report-14.0.1.2.0.dist-info/METADATA
odoo14_addon_l10n_it_financial_statements_report-14.0.1.2.0.dist-info/WHEEL
odoo14_addon_l10n_it_financial_statements_report-14.0.1.2.0.dist-info/top_level.txt
odoo14_addon_l10n_it_financial_statements_report-14.0.1.2.0.dist-info/RECORD
