Metadata-Version: 2.1
Name: odoo14-addon-l10n_it_financial_statements_report
Version: 14.0.1.2.0
Summary: Rendicontazione .pdf e .xls per stato patrimoniale e conto economico a sezioni contrapposte
Home-page: https://github.com/OCA/l10n-italy/tree/14.0/l10n_it_financial_statements_report
Author: Odoo Community Association (OCA), Openforce
Author-email: support@odoo-community.org
License: AGPL-3
Classifier: Programming Language :: Python
Classifier: Framework :: Odoo
Classifier: Framework :: Odoo :: 14.0
Classifier: License :: OSI Approved :: GNU Affero General Public License v3
Requires-Python: >=3.6
Requires-Dist: odoo14-addon-account-financial-report
Requires-Dist: odoo14-addon-account-menu
Requires-Dist: odoo14-addon-l10n-it-account
Requires-Dist: odoo<14.1dev,>=14.0a
Requires-Dist: openupgradelib
